loguru/__init__.py
loguru/cli.py
loguru/core/__init__.py
loguru/core/cli_app.py
loguru/core/fs_log_rag.py
loguru/core/tool_impls.py
loguru/core/models/__init__.py
loguru/core/models/config.py
loguru_cli-0.0.9.dist-info/LICENSE
loguru_cli-0.0.9.dist-info/METADATA
loguru_cli-0.0.9.dist-info/WHEEL
loguru_cli-0.0.9.dist-info/entry_points.txt
loguru_cli-0.0.9.dist-info/top_level.txt
loguru_cli-0.0.9.dist-info/RECORD
