Metadata-Version: 2.1
Name: loguru-cli
Version: 0.0.9
Summary: An interactive commandline interface that brings intelligence to your logs.
Author: Amith Koujalgi
Author-email: koujalgi.amith@gmail.com
Project-URL: Repository, https://github.com/Loguru-AI/Loguru-CLI
Classifier: Intended Audience :: Developers
Classifier: Operating System :: OS Independent
Classifier: Programming Language :: Python :: 3
Classifier: Programming Language :: Python :: 3.10
Classifier: Environment :: Console
License-File: LICENSE
Requires-Dist: prettytable ==3.10.2
Requires-Dist: langchain-community ==0.2.7
Requires-Dist: langchain-experimental ==0.0.62
Requires-Dist: langchain-huggingface ==0.0.3
Requires-Dist: sentence-transformers ==3.0.1
Requires-Dist: faiss-cpu ==1.8.0.post1
Requires-Dist: langchain-google-genai ==1.0.8
